{"name":"Image2fits","tagline":"Convert RGB image file (PNG, JPG, etc) to three FITS files (R, G, and B)","body":"# Usage\r\n\r\n```sh \r\npython image2fits.py --help\r\n```\r\n\r\n```\r\n: usage: image2fits.py [-h] file\r\n: \r\n: Convert an RGB or Grayscale image to FITS format\r\n: \r\n: positional arguments:\r\n:   file        Image file to convert\r\n: \r\n: optional arguments:\r\n:   -h, --help  show this help message and exit\r\n```\r\n","google":"","note":"Don't delete this file! It's used internally to help with page regeneration."}